dyz.py
dyz-0.11.12.dist-info/METADATA
dyz-0.11.12.dist-info/WHEEL
dyz-0.11.12.dist-info/entry_points.txt
dyz-0.11.12.dist-info/top_level.txt
dyz-0.11.12.dist-info/RECORD
